groupcorr/__init__.py
groupcorr/exceptions.py
groupcorr/groupcorr.py
groupcorr/utils.py
groupcorr-0.1.0.dist-info/METADATA
groupcorr-0.1.0.dist-info/WHEEL
groupcorr-0.1.0.dist-info/top_level.txt
groupcorr-0.1.0.dist-info/RECORD
